genquiz/MML2OMML.XSL
genquiz/__init__.py
genquiz/generator.py
genquiz/grader.py
genquiz-1.0.7.dist-info/LICENSE
genquiz-1.0.7.dist-info/METADATA
genquiz-1.0.7.dist-info/WHEEL
genquiz-1.0.7.dist-info/top_level.txt
genquiz-1.0.7.dist-info/RECORD
